tad_mctc/__init__.py
tad_mctc/_version.py
tad_mctc/py.typed
tad_mctc/autograd/__init__.py
tad_mctc/autograd/batched.py
tad_mctc/autograd/checks.py
tad_mctc/autograd/compat.py
tad_mctc/autograd/gradcheck.py
tad_mctc/autograd/hessian.py
tad_mctc/autograd/internals.py
tad_mctc/autograd/nonfunctorch.py
tad_mctc/batch/__init__.py
tad_mctc/batch/agnostic.py
tad_mctc/batch/merging.py
tad_mctc/batch/packing.py
tad_mctc/batch/sorting.py
tad_mctc/batch/unpacking.py
tad_mctc/batch/mask/__init__.py
tad_mctc/batch/mask/atoms.py
tad_mctc/batch/mask/jit.py
tad_mctc/batch/mask/pairs.py
tad_mctc/batch/mask/triples.py
tad_mctc/convert/__init__.py
tad_mctc/convert/numpy.py
tad_mctc/convert/pse.py
tad_mctc/convert/pytorch.py
tad_mctc/convert/tensor.py
tad_mctc/data/__init__.py
tad_mctc/data/en.py
tad_mctc/data/getters.py
tad_mctc/data/hardness.py
tad_mctc/data/mass.py
tad_mctc/data/molecules.py
tad_mctc/data/pse.py
tad_mctc/data/radii.py
tad_mctc/data/vdw-pairwise.pt
tad_mctc/data/zeff.py
tad_mctc/exceptions/__init__.py
tad_mctc/exceptions/io.py
tad_mctc/exceptions/molecule.py
tad_mctc/exceptions/pytorch.py
tad_mctc/io/__init__.py
tad_mctc/io/checks/__init__.py
tad_mctc/io/checks/molecule.py
tad_mctc/io/checks/shape.py
tad_mctc/io/read/__init__.py
tad_mctc/io/read/dotfiles.py
tad_mctc/io/read/frompath.py
tad_mctc/io/read/orca.py
tad_mctc/io/read/qcschema.py
tad_mctc/io/read/reader.py
tad_mctc/io/read/tblite.py
tad_mctc/io/read/turbomole.py
tad_mctc/io/read/xyz.py
tad_mctc/io/write/__init__.py
tad_mctc/io/write/topath.py
tad_mctc/io/write/turbomole.py
tad_mctc/io/write/writer.py
tad_mctc/io/write/xyz.py
tad_mctc/math/__init__.py
tad_mctc/math/einsum.py
tad_mctc/molecule/__init__.py
tad_mctc/molecule/bond.py
tad_mctc/molecule/container.py
tad_mctc/molecule/geometry.py
tad_mctc/molecule/property.py
tad_mctc/ncoord/__init__.py
tad_mctc/ncoord/count.py
tad_mctc/ncoord/d3.py
tad_mctc/ncoord/d4.py
tad_mctc/ncoord/defaults.py
tad_mctc/ncoord/eeq.py
tad_mctc/storch/__init__.py
tad_mctc-0.5.3.dist-info/licenses/LICENSE
tad_mctc-0.5.3.dist-info/METADATA
tad_mctc-0.5.3.dist-info/WHEEL
tad_mctc-0.5.3.dist-info/top_level.txt
tad_mctc-0.5.3.dist-info/RECORD
