Metadata-Version: 2.4
Name: tad_mctc
Version: 0.5.3
Summary: Torch Autodiff Utility
Home-page: https://github.com/tad-mctc/tad-mctc
Author: "Marvin Friede"
License: Apache-2.0
Project-URL: Documentation, https://tad-mctc.readthedocs.io
Project-URL: Source, https://github.com/tad-mctc/tad-mctc
Project-URL: Tracker, https://github.com/tad-mctc/tad-mctc/issues
Keywords: pytorch,autograd,computational chemistry,quantum chemistry
Classifier: Intended Audience :: Science/Research
Classifier: Natural Language :: English
Classifier: Operating System :: OS Independent
Classifier: Programming Language :: Python :: 3
Classifier: Programming Language :: Python :: 3 :: Only
Classifier: Programming Language :: Python :: 3.8
Classifier: Programming Language :: Python :: 3.9
Classifier: Programming Language :: Python :: 3.10
Classifier: Programming Language :: Python :: 3.11
Classifier: Programming Language :: Python :: 3.12
Classifier: Programming Language :: Python :: Implementation :: CPython
Classifier: Topic :: Scientific/Engineering
Classifier: Typing :: Typed
Requires-Python: <3.13,>=3.8
License-File: LICENSE
Requires-Dist: numpy<2
Requires-Dist: opt-einsum
Requires-Dist: psutil
Requires-Dist: qcelemental
Requires-Dist: torch<3,>=1.11
Requires-Dist: typing-extensions
Provides-Extra: dev
Requires-Dist: black; extra == "dev"
Requires-Dist: covdefaults; extra == "dev"
Requires-Dist: mypy; extra == "dev"
Requires-Dist: pre-commit; extra == "dev"
Requires-Dist: pylint; extra == "dev"
Requires-Dist: pytest; extra == "dev"
Requires-Dist: pytest-cov; extra == "dev"
Requires-Dist: pytest-random-order; extra == "dev"
Requires-Dist: pytest-rerunfailures; extra == "dev"
Requires-Dist: pytest-xdist; extra == "dev"
Requires-Dist: scipy; extra == "dev"
Requires-Dist: tox; extra == "dev"
Provides-Extra: tox
Requires-Dist: covdefaults; extra == "tox"
Requires-Dist: pytest; extra == "tox"
Requires-Dist: pytest-cov; extra == "tox"
Requires-Dist: pytest-random-order; extra == "tox"
Requires-Dist: pytest-rerunfailures; extra == "tox"
Requires-Dist: pytest-xdist; extra == "tox"
Requires-Dist: scipy; extra == "tox"
Dynamic: license-file
